tests/__init__.py
tests/test_api.py
ybai_sdk/__init__.py
ybai_sdk/api.py
ybai_sdk/utils.py
YellowBalloonAI-0.0.1.dist-info/METADATA
YellowBalloonAI-0.0.1.dist-info/WHEEL
YellowBalloonAI-0.0.1.dist-info/top_level.txt
YellowBalloonAI-0.0.1.dist-info/RECORD
