Metadata-Version: 2.1
Name: YellowBalloonAI
Version: 0.0.1
Summary: A ybtour Ai SDK for interacting with an API
Home-page: https://github.com/crimebbo/ybai_sdk
Author: 박재형
Author-email: crimebbo@ybtour.co.kr
Classifier: Programming Language :: Python :: 3
Classifier: License :: OSI Approved :: MIT License
Classifier: Operating System :: OS Independent
Requires-Python: >=3.6
Requires-Dist: requests
